apigee_ci_tool/__init__.py
apigee_ci_tool/policyParser.py
apigee_ci_tool-0.0.1.dist-info/LICENCE
apigee_ci_tool-0.0.1.dist-info/METADATA
apigee_ci_tool-0.0.1.dist-info/WHEEL
apigee_ci_tool-0.0.1.dist-info/top_level.txt
apigee_ci_tool-0.0.1.dist-info/RECORD
