Metadata-Version: 2.1
Name: apigee-ci-tool
Version: 0.0.1
Summary: A module with tools to make Apigee CICD easier.
Home-page: https://github.com/GingRick/apigee-ci-tool
Author: Ricardo Santamaria
Author-email: ricardo.santamariah@gmail.com
License: UNKNOWN
Platform: UNKNOWN
Classifier: Programming Language :: Python :: 2
Classifier: License :: OSI Approved :: MIT License
Classifier: Operating System :: OS Independent
Requires-Python: >=2.7
